{
  "QualifiedValues": [
    {
      "Kind": "default.cds_cr216_kdcuser_forms",
      "Namespace": "KDC Users (Forms)",
      "Values": {
        "Information": "8d6996e2-4224-4269-8d2d-dd51168c4589"
      }
    },
    {
      "Kind": "default.cds_cr216_dcopsonboarding_forms",
      "Namespace": "DC Ops Onboardings (Forms)",
      "Values": {
        "Information": "5d6ff8a1-202e-42c0-9713-c8df0e5eb6a0"
      }
    },
    {
      "Kind": "default.cds_systemuser_forms",
      "Namespace": "Users (Forms)",
      "Values": {
        "Application User": "d26924ef-4d80-46f7-ab1d-e6ae80a54ce8",
        "Information": "094fb08a-77bb-49e0-b7ea-8dbddfd01294",
        "Quick User Information": "ad33f48b-f0a1-eb11-b1ac-00224855d2ba",
        "User": "c2cd9e55-d4b4-4b55-9951-16ead79643e5",
        "User form – Business": "c2413504-7eb2-4c59-a087-95d819866114",
        "User Hierarchy Tile Form": "c68d6c09-d7a7-4959-8d0f-44b8cff9b452"
      }
    },
    {
      "Kind": "default.cds_team_forms",
      "Namespace": "Teams (Forms)",
      "Values": {
        "Information": "f5cfab6a-d4c2-4519-b68f-6e7485432e29",
        "New Form": "a9012f85-915a-4349-b3b4-62ff2040e87c",
        "Team": "7ba7fac1-1418-4335-935f-f7f8dfd73fcc",
        "Team form – Business": "4aabf594-b30a-490d-bf97-89c67c6777fe"
      }
    },
    {
      "Kind": "default.cds_businessunit_forms",
      "Namespace": "Business Units (Forms)",
      "Values": {
        "Business Unit Hierarchy Form": "405b16b6-126a-4117-a4e0-33f0caf0c7a2",
        "Information": "ca8dfced-338c-43b2-b212-83745e257c28"
      }
    },
    {
      "Kind": "default.cds_cr216_testtable_forms",
      "Namespace": "TestTables (Forms)",
      "Values": {
        "Information": "64d18e55-c15d-47eb-9cf1-ef1778b6280e"
      }
    },
    {
      "Kind": "default.cds_kdc_vendor_master_forms",
      "Namespace": "Vendor_Masters (Forms)",
      "Values": {
        "Information": "3448c224-7512-44ab-a688-e7fc0a269357"
      }
    }
  ]
}